{
  "timestamp": "2025-09-02T19:03:04.149Z",
  "data": [
    {
      "chainId": 42161,
      "protocol": "uniswapv3",
      "address": "0x547a116a2622876ce1c8d19d41c683c8f7bec5c0",
      "tvlUSD": "37630.895186509726",
      "feeApr": 0.0011851953511250947,
      "rewardApr": 0.07232498280366018,
      "lastUpdated": "2025-09-02T19:02:00.464000",
      "token0TvlUsd": 13290.602679885731,
      "token1TvlUsd": 24340.292506623995,
      "totalSupply": "36015686578",
      "rewardsDetails": []
    },
    {
      "chainId": 42161,
      "protocol": "uniswapv3",
      "address": "0x52ee1ffba696c5e9b0bc177a9f8a3098420ea691",
      "tvlUSD": "21057.041404291223",
      "feeApr": 1.152819080350848,
      "rewardApr": 0,
      "lastUpdated": "2025-09-02T19:02:00.439000",
      "token0TvlUsd": 9003.161925890881,
      "token1TvlUsd": 12053.879478400344,
      "totalSupply": "3203560953968871001",
      "rewardsDetails": []
    },
    {
      "chainId": 42161,
      "protocol": "uniswapv3",
      "address": "0x330dfc5bc1a63a1dcf1cd5bc9ad3d5e5e61bcb6c",
      "tvlUSD": "1287.4885934742692",
      "feeApr": 1.343489546294758,
      "rewardApr": 0,
      "lastUpdated": "2025-09-02T19:02:00.356000",
      "token0TvlUsd": 675.848817232377,
      "token1TvlUsd": 611.6397762418922,
      "totalSupply": "4432154182743125711323",
      "rewardsDetails": []
    },
    {
      "chainId": 42161,
      "protocol": "uniswapv3",
      "address": "0xfa392dbefd2d5ec891ef5aeb87397a89843a8260",
      "tvlUSD": "51509.81769369152",
      "feeApr": 1.0972311650476667,
      "rewardApr": 0,
      "lastUpdated": "2025-09-02T19:02:00.856000",
      "token0TvlUsd": 34272.88392951375,
      "token1TvlUsd": 17236.933764177767,
      "totalSupply": "2727196666938613527846",
      "rewardsDetails": []
    },
    {
      "chainId": 42161,
      "protocol": "uniswapv3",
      "address": "0xf08bdbc590c59cb7b27a8d224e419ef058952b5f",
      "tvlUSD": "10207.850596161386",
      "feeApr": 4.1508216093060515,
      "rewardApr": 0,
      "lastUpdated": "2025-09-02T19:02:00.817000",
      "token0TvlUsd": 9596.536387802467,
      "token1TvlUsd": 611.3142083589195,
      "totalSupply": "308137518155478858207",
      "rewardsDetails": []
    },
    {
      "chainId": 42161,
      "protocol": "uniswapv3",
      "address": "0x2bcbdd577616357464cfe307bc67f9e820a66e80",
      "tvlUSD": "2078.8088719175857",
      "feeApr": 0.12790366391553643,
      "rewardApr": 0,
      "lastUpdated": "2025-09-02T19:02:00.340000",
      "token0TvlUsd": 1926.5028116157903,
      "token1TvlUsd": 152.3060603017954,
      "totalSupply": "7395423310061475350",
      "rewardsDetails": []
    }
  ]
}