{
  "timestamp": "2025-12-06T22:14:24.915Z",
  "data": [
    {
      "chainId": 42161,
      "protocol": "uniswapv3",
      "address": "0x547a116a2622876ce1c8d19d41c683c8f7bec5c0",
      "tvlUSD": "2299.4103867830236",
      "feeApr": 0.00029605930664182905,
      "rewardApr": 0,
      "lastUpdated": "2025-12-06T22:01:29.654000",
      "token0TvlUsd": 2250.2009027830236,
      "token1TvlUsd": 49.209484,
      "totalSupply": "2204730609",
      "rewardsDetails": []
    },
    {
      "chainId": 42161,
      "protocol": "uniswapv3",
      "address": "0x52ee1ffba696c5e9b0bc177a9f8a3098420ea691",
      "tvlUSD": "10359.659548147329",
      "feeApr": 0.06530608027079923,
      "rewardApr": 0,
      "lastUpdated": "2025-12-06T22:01:29.642000",
      "token0TvlUsd": 7692.140003382272,
      "token1TvlUsd": 2667.5195447650563,
      "totalSupply": "1956716479867344104",
      "rewardsDetails": []
    },
    {
      "chainId": 42161,
      "protocol": "uniswapv3",
      "address": "0x330dfc5bc1a63a1dcf1cd5bc9ad3d5e5e61bcb6c",
      "tvlUSD": "614.3451262381195",
      "feeApr": 0.6575258866750131,
      "rewardApr": 0,
      "lastUpdated": "2025-12-06T22:01:29.561000",
      "token0TvlUsd": 263.82359250542396,
      "token1TvlUsd": 350.52153373269556,
      "totalSupply": "4432154182743125711323",
      "rewardsDetails": []
    },
    {
      "chainId": 42161,
      "protocol": "uniswapv3",
      "address": "0xfa392dbefd2d5ec891ef5aeb87397a89843a8260",
      "tvlUSD": "32706.709412606848",
      "feeApr": 0.862901997487084,
      "rewardApr": 0,
      "lastUpdated": "2025-12-06T22:01:29.980000",
      "token0TvlUsd": 25555.630153405662,
      "token1TvlUsd": 7151.079259201186,
      "totalSupply": "2715261950902246862637",
      "rewardsDetails": []
    },
    {
      "chainId": 42161,
      "protocol": "uniswapv3",
      "address": "0xf08bdbc590c59cb7b27a8d224e419ef058952b5f",
      "tvlUSD": "6923.674111909194",
      "feeApr": 2.0529763860925545,
      "rewardApr": 0,
      "lastUpdated": "2025-12-06T22:01:29.943000",
      "token0TvlUsd": 2478.2746578739916,
      "token1TvlUsd": 4445.399454035202,
      "totalSupply": "174583206644209293769",
      "rewardsDetails": []
    },
    {
      "chainId": 42161,
      "protocol": "uniswapv3",
      "address": "0x2bcbdd577616357464cfe307bc67f9e820a66e80",
      "tvlUSD": "563.2042384211549",
      "feeApr": 0.06395118491952098,
      "rewardApr": 0,
      "lastUpdated": "2025-12-06T22:01:29.550000",
      "token0TvlUsd": 524.6030243056015,
      "token1TvlUsd": 38.601214115553425,
      "totalSupply": "5605346197713434383",
      "rewardsDetails": []
    }
  ]
}