{
  "timestamp": "2025-10-16T20:03:56.982Z",
  "data": [
    {
      "chainId": 42161,
      "protocol": "uniswapv3",
      "address": "0x547a116a2622876ce1c8d19d41c683c8f7bec5c0",
      "tvlUSD": "13378.399788296549",
      "feeApr": 0.00032012081612209673,
      "rewardApr": 0.08734807911007504,
      "lastUpdated": "2025-10-16T20:01:04.303000",
      "token0TvlUsd": 9297.516064438187,
      "token1TvlUsd": 4080.883723858363,
      "totalSupply": "12818494125",
      "rewardsDetails": []
    },
    {
      "chainId": 42161,
      "protocol": "uniswapv3",
      "address": "0x52ee1ffba696c5e9b0bc177a9f8a3098420ea691",
      "tvlUSD": "12516.17729183344",
      "feeApr": 0,
      "rewardApr": 0,
      "lastUpdated": "2025-10-16T20:01:04.278000",
      "token0TvlUsd": 11007.584507512283,
      "token1TvlUsd": 1508.592784321157,
      "totalSupply": "1999731824297410228",
      "rewardsDetails": []
    },
    {
      "chainId": 42161,
      "protocol": "uniswapv3",
      "address": "0x330dfc5bc1a63a1dcf1cd5bc9ad3d5e5e61bcb6c",
      "tvlUSD": "914.3445788137885",
      "feeApr": 4.689341928761719,
      "rewardApr": 0,
      "lastUpdated": "2025-10-16T20:01:04.217000",
      "token0TvlUsd": 203.2779036058981,
      "token1TvlUsd": 711.0666752078904,
      "totalSupply": "4432154182743125711323",
      "rewardsDetails": []
    },
    {
      "chainId": 42161,
      "protocol": "uniswapv3",
      "address": "0xfa392dbefd2d5ec891ef5aeb87397a89843a8260",
      "tvlUSD": "40776.28809534258",
      "feeApr": 6.809748599145505,
      "rewardApr": 0,
      "lastUpdated": "2025-10-16T20:01:04.728000",
      "token0TvlUsd": 12812.198622150874,
      "token1TvlUsd": 27964.089473191707,
      "totalSupply": "2717530506825025982972",
      "rewardsDetails": []
    },
    {
      "chainId": 42161,
      "protocol": "uniswapv3",
      "address": "0xf08bdbc590c59cb7b27a8d224e419ef058952b5f",
      "tvlUSD": "6355.592047677277",
      "feeApr": 19.992617271896126,
      "rewardApr": 0,
      "lastUpdated": "2025-10-16T20:01:04.686000",
      "token0TvlUsd": 1932.0061781047532,
      "token1TvlUsd": 4423.585869572524,
      "totalSupply": "178705735071537923405",
      "rewardsDetails": []
    },
    {
      "chainId": 42161,
      "protocol": "uniswapv3",
      "address": "0x2bcbdd577616357464cfe307bc67f9e820a66e80",
      "tvlUSD": "1169.7580378453126",
      "feeApr": 0.6352543732608235,
      "rewardApr": 0,
      "lastUpdated": "2025-10-16T20:01:04.203000",
      "token0TvlUsd": 1169.5415025986924,
      "token1TvlUsd": 0.21653524662024115,
      "totalSupply": "5605346197713434383",
      "rewardsDetails": []
    }
  ]
}