{
  "timestamp": "2026-02-09T06:25:16.361Z",
  "data": [
    {
      "chainId": 42161,
      "protocol": "uniswapv3",
      "address": "0x547a116a2622876ce1c8d19d41c683c8f7bec5c0",
      "tvlUSD": "2266.7608191824265",
      "feeApr": 0.00299740617540329,
      "rewardApr": 0,
      "lastUpdated": "2026-02-09T06:00:58.893000",
      "token0TvlUsd": 2265.0275411824264,
      "token1TvlUsd": 1.733278,
      "totalSupply": "2190596432",
      "rewardsDetails": []
    },
    {
      "chainId": 42161,
      "protocol": "uniswapv3",
      "address": "0x52ee1ffba696c5e9b0bc177a9f8a3098420ea691",
      "tvlUSD": "10171.61498653997",
      "feeApr": 0,
      "rewardApr": 0,
      "lastUpdated": "2026-02-09T06:00:58.875000",
      "token0TvlUsd": 857.3092778157717,
      "token1TvlUsd": 9314.305708724198,
      "totalSupply": "2694448704321546928",
      "rewardsDetails": []
    },
    {
      "chainId": 42161,
      "protocol": "uniswapv3",
      "address": "0x330dfc5bc1a63a1dcf1cd5bc9ad3d5e5e61bcb6c",
      "tvlUSD": "392.8840181721152",
      "feeApr": 1.5266972353095696,
      "rewardApr": 0,
      "lastUpdated": "2026-02-09T06:00:58.792000",
      "token0TvlUsd": 35.857305153321356,
      "token1TvlUsd": 357.0267130187938,
      "totalSupply": "4432154182743125711323",
      "rewardsDetails": []
    },
    {
      "chainId": 42161,
      "protocol": "uniswapv3",
      "address": "0xfa392dbefd2d5ec891ef5aeb87397a89843a8260",
      "tvlUSD": "21510.624832412173",
      "feeApr": 0.5158048621383499,
      "rewardApr": 0,
      "lastUpdated": "2026-02-09T06:00:59.305000",
      "token0TvlUsd": 10415.118284205504,
      "token1TvlUsd": 11095.50654820667,
      "totalSupply": "2704192453330892671227",
      "rewardsDetails": []
    },
    {
      "chainId": 42161,
      "protocol": "uniswapv3",
      "address": "0xf08bdbc590c59cb7b27a8d224e419ef058952b5f",
      "tvlUSD": "4900.776834386634",
      "feeApr": 0.6966439682101331,
      "rewardApr": 0,
      "lastUpdated": "2026-02-09T06:00:59.263000",
      "token0TvlUsd": 2507.647612463104,
      "token1TvlUsd": 2393.1292219235297,
      "totalSupply": "149031727236076975641",
      "rewardsDetails": []
    },
    {
      "chainId": 42161,
      "protocol": "uniswapv3",
      "address": "0x2bcbdd577616357464cfe307bc67f9e820a66e80",
      "tvlUSD": "522.3640498845981",
      "feeApr": 0,
      "rewardApr": 0,
      "lastUpdated": "2026-02-09T06:00:58.775000",
      "token0TvlUsd": 517.9909343500499,
      "token1TvlUsd": 4.373115534548196,
      "totalSupply": "5605346197713434383",
      "rewardsDetails": []
    }
  ]
}