{
  "timestamp": "2025-04-08T06:04:49.415Z",
  "data": [
    {
      "chainId": 42161,
      "protocol": "uniswapv3",
      "address": "0x547a116a2622876ce1c8d19d41c683c8f7bec5c0",
      "tvlUSD": "173305.0499508212",
      "feeApr": 0.0032940293424579123,
      "rewardApr": 0.037101020632767774,
      "rewardsDetails": [
        {
          "rewarderAddress": "0xf178d158bcc02f36ee990cab8e9880bf0679dc9a163adca85d2b041480a10248",
          "rewardToken": "0xf5a27e55c748bcddbfea5477cb9ae924f0f7fd2e",
          "rewardTokenDecimals": 18,
          "rewardTokenSymbol": "TST",
          "rewardPerSecond": "4.046752469951381e+16",
          "apr": 0.037101020632767774
        }
      ],
      "lastUpdated": "2025-04-08T06:03:03.104000",
      "token0TvlUsd": 156281.17795863093,
      "token1TvlUsd": 17023.87199219028,
      "totalSupply": "169695780825"
    },
    {
      "chainId": 42161,
      "protocol": "uniswapv3",
      "address": "0x52ee1ffba696c5e9b0bc177a9f8a3098420ea691",
      "tvlUSD": "325450.5760403209",
      "feeApr": 0.9342646647687843,
      "rewardApr": 0,
      "rewardsDetails": [],
      "lastUpdated": "2025-04-08T06:03:03.104000",
      "token0TvlUsd": 30606.829230879226,
      "token1TvlUsd": 294843.7468094417,
      "totalSupply": "73999907682642504031"
    },
    {
      "chainId": 42161,
      "protocol": "uniswapv3",
      "address": "0x330dfc5bc1a63a1dcf1cd5bc9ad3d5e5e61bcb6c",
      "tvlUSD": "460.3103136175847",
      "feeApr": 1.9044579299042854,
      "rewardApr": 0,
      "rewardsDetails": [],
      "lastUpdated": "2025-04-08T06:03:03.104000",
      "token0TvlUsd": 214.0296383211004,
      "token1TvlUsd": 246.2806752964843,
      "totalSupply": "1726878582169481743143"
    },
    {
      "chainId": 42161,
      "protocol": "uniswapv3",
      "address": "0xfa392dbefd2d5ec891ef5aeb87397a89843a8260",
      "tvlUSD": "20365.9125320314",
      "feeApr": 0.739322913686224,
      "rewardApr": 0,
      "rewardsDetails": [
        {
          "rewarderAddress": "0x6348eda687b6fc4238cdfaa6ca36bb6196d867d3",
          "rewardToken": "0x18c11fd286c5ec11c3b683caa813b77f5163a122",
          "rewardTokenDecimals": 18,
          "rewardTokenSymbol": "GNS",
          "rewardPerSecond": 0,
          "apr": 0
        },
        {
          "rewarderAddress": "0x6be9b5925c9f5833493ae6e7ffb3a0d745f0f235",
          "rewardToken": "0x912ce59144191c1204e64559fe8253a0e49e6548",
          "rewardTokenDecimals": 18,
          "rewardTokenSymbol": "ARB",
          "rewardPerSecond": 0,
          "apr": 0
        },
        {
          "rewarderAddress": "0xf1778f0b5549df305fab2cd31a46ee8c78dfa546",
          "rewardToken": "0x912ce59144191c1204e64559fe8253a0e49e6548",
          "rewardTokenDecimals": 18,
          "rewardTokenSymbol": "ARB",
          "rewardPerSecond": 0,
          "apr": 0
        }
      ],
      "lastUpdated": "2025-04-08T06:03:03.106000",
      "token0TvlUsd": 15294.366191446607,
      "token1TvlUsd": 5071.546340584795,
      "totalSupply": "2242209390229130710850"
    },
    {
      "chainId": 42161,
      "protocol": "uniswapv3",
      "address": "0xf08bdbc590c59cb7b27a8d224e419ef058952b5f",
      "tvlUSD": "6933.312416670908",
      "feeApr": 39.61160704829025,
      "rewardApr": 0,
      "rewardsDetails": [],
      "lastUpdated": "2025-04-08T06:03:03.106000",
      "token0TvlUsd": 2847.221415931845,
      "token1TvlUsd": 4086.0910007390626,
      "totalSupply": "262317943590035072930"
    },
    {
      "chainId": 42161,
      "protocol": "uniswapv3",
      "address": "0x2bcbdd577616357464cfe307bc67f9e820a66e80",
      "tvlUSD": "2516.175035115608",
      "feeApr": 1.0130251037192701,
      "rewardApr": 0,
      "rewardsDetails": [
        {
          "rewarderAddress": "0x6348eda687b6fc4238cdfaa6ca36bb6196d867d3",
          "rewardToken": "0x18c11fd286c5ec11c3b683caa813b77f5163a122",
          "rewardTokenDecimals": 18,
          "rewardTokenSymbol": "GNS",
          "rewardPerSecond": 0,
          "apr": 0
        },
        {
          "rewarderAddress": "0x6be9b5925c9f5833493ae6e7ffb3a0d745f0f235",
          "rewardToken": "0x912ce59144191c1204e64559fe8253a0e49e6548",
          "rewardTokenDecimals": 18,
          "rewardTokenSymbol": "ARB",
          "rewardPerSecond": 0,
          "apr": 0
        },
        {
          "rewarderAddress": "0xf1778f0b5549df305fab2cd31a46ee8c78dfa546",
          "rewardToken": "0x912ce59144191c1204e64559fe8253a0e49e6548",
          "rewardTokenDecimals": 18,
          "rewardTokenSymbol": "ARB",
          "rewardPerSecond": 0,
          "apr": 0
        }
      ],
      "lastUpdated": "2025-04-08T06:03:03.104000",
      "token0TvlUsd": 2092.984211151299,
      "token1TvlUsd": 423.19082396430895,
      "totalSupply": "7395423310061475350"
    }
  ]
}