{
  "timestamp": "2025-10-27T04:09:42.554Z",
  "data": [
    {
      "chainId": 42161,
      "protocol": "uniswapv3",
      "address": "0x547a116a2622876ce1c8d19d41c683c8f7bec5c0",
      "tvlUSD": "13368.05383302715",
      "feeApr": 0.00006801029032373465,
      "rewardApr": 0.08092325073359521,
      "lastUpdated": "2025-10-27T04:01:17.513000",
      "token0TvlUsd": 9289.268050404791,
      "token1TvlUsd": 4078.7857826223594,
      "totalSupply": "12818672140",
      "rewardsDetails": []
    },
    {
      "chainId": 42161,
      "protocol": "uniswapv3",
      "address": "0x52ee1ffba696c5e9b0bc177a9f8a3098420ea691",
      "tvlUSD": "13201.28547394504",
      "feeApr": 0.20712602741072375,
      "rewardApr": 0,
      "lastUpdated": "2025-10-27T04:01:17.495000",
      "token0TvlUsd": 13119.434454447097,
      "token1TvlUsd": 81.85101949794343,
      "totalSupply": "1960952683462083396",
      "rewardsDetails": []
    },
    {
      "chainId": 42161,
      "protocol": "uniswapv3",
      "address": "0x330dfc5bc1a63a1dcf1cd5bc9ad3d5e5e61bcb6c",
      "tvlUSD": "1011.1976574875198",
      "feeApr": 0.8060127318311543,
      "rewardApr": 0,
      "lastUpdated": "2025-10-27T04:01:17.423000",
      "token0TvlUsd": 634.128169623762,
      "token1TvlUsd": 377.06948786375773,
      "totalSupply": "4432154182743125711323",
      "rewardsDetails": []
    },
    {
      "chainId": 42161,
      "protocol": "uniswapv3",
      "address": "0xfa392dbefd2d5ec891ef5aeb87397a89843a8260",
      "tvlUSD": "44787.37508821467",
      "feeApr": 2.181207021896541,
      "rewardApr": 0,
      "lastUpdated": "2025-10-27T04:01:17.918000",
      "token0TvlUsd": 19472.684392104544,
      "token1TvlUsd": 25314.690696110123,
      "totalSupply": "2717529942352646986140",
      "rewardsDetails": []
    },
    {
      "chainId": 42161,
      "protocol": "uniswapv3",
      "address": "0xf08bdbc590c59cb7b27a8d224e419ef058952b5f",
      "tvlUSD": "7182.719438062798",
      "feeApr": 4.477834399349114,
      "rewardApr": 0,
      "lastUpdated": "2025-10-27T04:01:17.876000",
      "token0TvlUsd": 2058.0508668651373,
      "token1TvlUsd": 5124.668571197661,
      "totalSupply": "178705735071537923405",
      "rewardsDetails": []
    },
    {
      "chainId": 42161,
      "protocol": "uniswapv3",
      "address": "0x2bcbdd577616357464cfe307bc67f9e820a66e80",
      "tvlUSD": "1023.8046242835234",
      "feeApr": 0.0648908969859422,
      "rewardApr": 0,
      "lastUpdated": "2025-10-27T04:01:17.411000",
      "token0TvlUsd": 1023.5453158907436,
      "token1TvlUsd": 0.25930839277971246,
      "totalSupply": "5605346197713434383",
      "rewardsDetails": []
    }
  ]
}