{
  "timestamp": "2025-10-26T22:03:32.251Z",
  "data": [
    {
      "chainId": 42161,
      "protocol": "uniswapv3",
      "address": "0x547a116a2622876ce1c8d19d41c683c8f7bec5c0",
      "tvlUSD": "13372.0650272546",
      "feeApr": 0.00006801029032373465,
      "rewardApr": 0.08092325073359521,
      "lastUpdated": "2025-10-26T22:01:29.313000",
      "token0TvlUsd": 9292.659229386729,
      "token1TvlUsd": 4079.405797867873,
      "totalSupply": "12818672140",
      "rewardsDetails": []
    },
    {
      "chainId": 42161,
      "protocol": "uniswapv3",
      "address": "0x52ee1ffba696c5e9b0bc177a9f8a3098420ea691",
      "tvlUSD": "13015.327027715286",
      "feeApr": 0.20712602741072375,
      "rewardApr": 0,
      "lastUpdated": "2025-10-26T22:01:29.290000",
      "token0TvlUsd": 12536.803867710994,
      "token1TvlUsd": 478.5231600042924,
      "totalSupply": "1960952683462083396",
      "rewardsDetails": []
    },
    {
      "chainId": 42161,
      "protocol": "uniswapv3",
      "address": "0x330dfc5bc1a63a1dcf1cd5bc9ad3d5e5e61bcb6c",
      "tvlUSD": "968.4020692399015",
      "feeApr": 0.8060127318311543,
      "rewardApr": 0,
      "lastUpdated": "2025-10-26T22:01:29.200000",
      "token0TvlUsd": 389.54887369722456,
      "token1TvlUsd": 578.8531955426769,
      "totalSupply": "4432154182743125711323",
      "rewardsDetails": []
    },
    {
      "chainId": 42161,
      "protocol": "uniswapv3",
      "address": "0xfa392dbefd2d5ec891ef5aeb87397a89843a8260",
      "tvlUSD": "43208.56254951783",
      "feeApr": 2.181207021896541,
      "rewardApr": 0,
      "lastUpdated": "2025-10-26T22:01:29.702000",
      "token0TvlUsd": 11120.68843287969,
      "token1TvlUsd": 32087.874116638144,
      "totalSupply": "2717529942352646986140",
      "rewardsDetails": []
    },
    {
      "chainId": 42161,
      "protocol": "uniswapv3",
      "address": "0xf08bdbc590c59cb7b27a8d224e419ef058952b5f",
      "tvlUSD": "6997.832585409414",
      "feeApr": 4.477834399349114,
      "rewardApr": 0,
      "lastUpdated": "2025-10-26T22:01:29.678000",
      "token0TvlUsd": 1637.339360048955,
      "token1TvlUsd": 5360.493225360458,
      "totalSupply": "178705735071537923405",
      "rewardsDetails": []
    },
    {
      "chainId": 42161,
      "protocol": "uniswapv3",
      "address": "0x2bcbdd577616357464cfe307bc67f9e820a66e80",
      "tvlUSD": "993.3031694677571",
      "feeApr": 0.0648908969859422,
      "rewardApr": 0,
      "lastUpdated": "2025-10-26T22:01:29.185000",
      "token0TvlUsd": 992.9661832222187,
      "token1TvlUsd": 0.33698624553848366,
      "totalSupply": "5605346197713434383",
      "rewardsDetails": []
    }
  ]
}