{
  "timestamp": "2025-12-06T05:15:29.161Z",
  "data": [
    {
      "chainId": 42161,
      "protocol": "uniswapv3",
      "address": "0x547a116a2622876ce1c8d19d41c683c8f7bec5c0",
      "tvlUSD": "2298.1959067607477",
      "feeApr": 0.00032609920186002663,
      "rewardApr": 0,
      "lastUpdated": "2025-12-06T05:01:12.217000",
      "token0TvlUsd": 2248.9864227607477,
      "token1TvlUsd": 49.209484,
      "totalSupply": "2204730609",
      "rewardsDetails": []
    },
    {
      "chainId": 42161,
      "protocol": "uniswapv3",
      "address": "0x52ee1ffba696c5e9b0bc177a9f8a3098420ea691",
      "tvlUSD": "10409.386282712034",
      "feeApr": 0.05564935004881266,
      "rewardApr": 0,
      "lastUpdated": "2025-12-06T05:01:12.207000",
      "token0TvlUsd": 7649.640066561648,
      "token1TvlUsd": 2759.7462161503854,
      "totalSupply": "1956716479867344104",
      "rewardsDetails": []
    },
    {
      "chainId": 42161,
      "protocol": "uniswapv3",
      "address": "0x330dfc5bc1a63a1dcf1cd5bc9ad3d5e5e61bcb6c",
      "tvlUSD": "601.7659930625626",
      "feeApr": 0.6082677247830243,
      "rewardApr": 0,
      "lastUpdated": "2025-12-06T05:01:12.127000",
      "token0TvlUsd": 73.55031908116912,
      "token1TvlUsd": 528.2156739813935,
      "totalSupply": "4432154182743125711323",
      "rewardsDetails": []
    },
    {
      "chainId": 42161,
      "protocol": "uniswapv3",
      "address": "0xfa392dbefd2d5ec891ef5aeb87397a89843a8260",
      "tvlUSD": "32423.71895609765",
      "feeApr": 0.6124384745111183,
      "rewardApr": 0,
      "lastUpdated": "2025-12-06T05:01:12.591000",
      "token0TvlUsd": 12772.510421534611,
      "token1TvlUsd": 19651.20853456304,
      "totalSupply": "2715261950902246862637",
      "rewardsDetails": []
    },
    {
      "chainId": 42161,
      "protocol": "uniswapv3",
      "address": "0xf08bdbc590c59cb7b27a8d224e419ef058952b5f",
      "tvlUSD": "6939.96520223789",
      "feeApr": 0.5105487825639534,
      "rewardApr": 0,
      "lastUpdated": "2025-12-06T05:01:12.555000",
      "token0TvlUsd": 5331.022330654251,
      "token1TvlUsd": 1608.9428715836384,
      "totalSupply": "174583206644209293769",
      "rewardsDetails": []
    },
    {
      "chainId": 42161,
      "protocol": "uniswapv3",
      "address": "0x2bcbdd577616357464cfe307bc67f9e820a66e80",
      "tvlUSD": "549.2263551211983",
      "feeApr": 0.03417505508037487,
      "rewardApr": 0,
      "lastUpdated": "2025-12-06T05:01:12.107000",
      "token0TvlUsd": 549.1536015966516,
      "token1TvlUsd": 0.07275352454668553,
      "totalSupply": "5605346197713434383",
      "rewardsDetails": []
    }
  ]
}