{
  "timestamp": "2026-01-27T02:45:53.366Z",
  "data": [
    {
      "chainId": 42161,
      "protocol": "uniswapv3",
      "address": "0x547a116a2622876ce1c8d19d41c683c8f7bec5c0",
      "tvlUSD": "2288.8052550822476",
      "feeApr": 0,
      "rewardApr": 0,
      "lastUpdated": "2026-01-27T02:30:50.050000",
      "token0TvlUsd": 2239.6035480822475,
      "token1TvlUsd": 49.201707,
      "totalSupply": "2199263355",
      "rewardsDetails": []
    },
    {
      "chainId": 42161,
      "protocol": "uniswapv3",
      "address": "0x52ee1ffba696c5e9b0bc177a9f8a3098420ea691",
      "tvlUSD": "10149.133264176255",
      "feeApr": 0.011938090477482876,
      "rewardApr": 0,
      "lastUpdated": "2026-01-27T02:30:50.044000",
      "token0TvlUsd": 367.9472022039765,
      "token1TvlUsd": 9781.186061972277,
      "totalSupply": "1951045960121303604",
      "rewardsDetails": []
    },
    {
      "chainId": 42161,
      "protocol": "uniswapv3",
      "address": "0x330dfc5bc1a63a1dcf1cd5bc9ad3d5e5e61bcb6c",
      "tvlUSD": "540.6775230989814",
      "feeApr": 0.46683060172465596,
      "rewardApr": 0,
      "lastUpdated": "2026-01-27T02:30:49.959000",
      "token0TvlUsd": 9.827553630021585,
      "token1TvlUsd": 530.8499694689598,
      "totalSupply": "4432154182743125711323",
      "rewardsDetails": []
    },
    {
      "chainId": 42161,
      "protocol": "uniswapv3",
      "address": "0xfa392dbefd2d5ec891ef5aeb87397a89843a8260",
      "tvlUSD": "29896.72376552957",
      "feeApr": 0.21945124201775287,
      "rewardApr": 0,
      "lastUpdated": "2026-01-27T02:30:50.345000",
      "token0TvlUsd": 9390.82249090518,
      "token1TvlUsd": 20505.901274624386,
      "totalSupply": "2716411797312088954114",
      "rewardsDetails": []
    },
    {
      "chainId": 42161,
      "protocol": "uniswapv3",
      "address": "0xf08bdbc590c59cb7b27a8d224e419ef058952b5f",
      "tvlUSD": "5773.525459684504",
      "feeApr": 8.52002073308045,
      "rewardApr": 0,
      "lastUpdated": "2026-01-27T02:30:50.310000",
      "token0TvlUsd": 2275.091110642535,
      "token1TvlUsd": 3498.4343490419697,
      "totalSupply": "149031727236076975641",
      "rewardsDetails": []
    },
    {
      "chainId": 42161,
      "protocol": "uniswapv3",
      "address": "0x2bcbdd577616357464cfe307bc67f9e820a66e80",
      "tvlUSD": "713.4145531497561",
      "feeApr": 0.12604814885761487,
      "rewardApr": 0,
      "lastUpdated": "2026-01-27T02:30:49.946000",
      "token0TvlUsd": 698.371765062131,
      "token1TvlUsd": 15.04278808762508,
      "totalSupply": "5605346197713434383",
      "rewardsDetails": []
    }
  ]
}