{
  "timestamp": "2026-02-09T17:19:19.025Z",
  "data": [
    {
      "chainId": 42161,
      "protocol": "uniswapv3",
      "address": "0x547a116a2622876ce1c8d19d41c683c8f7bec5c0",
      "tvlUSD": "2266.661768803103",
      "feeApr": 0.00299740617540329,
      "rewardApr": 0,
      "lastUpdated": "2026-02-09T17:01:03.324000",
      "token0TvlUsd": 2264.9284908031027,
      "token1TvlUsd": 1.733278,
      "totalSupply": "2190596432",
      "rewardsDetails": []
    },
    {
      "chainId": 42161,
      "protocol": "uniswapv3",
      "address": "0x52ee1ffba696c5e9b0bc177a9f8a3098420ea691",
      "tvlUSD": "10206.399745054037",
      "feeApr": 0,
      "rewardApr": 0,
      "lastUpdated": "2026-02-09T17:01:03.309000",
      "token0TvlUsd": 1664.864124637769,
      "token1TvlUsd": 8541.535620416269,
      "totalSupply": "2694448704321546928",
      "rewardsDetails": []
    },
    {
      "chainId": 42161,
      "protocol": "uniswapv3",
      "address": "0x330dfc5bc1a63a1dcf1cd5bc9ad3d5e5e61bcb6c",
      "tvlUSD": "379.81769476203556",
      "feeApr": 1.5266972353095696,
      "rewardApr": 0,
      "lastUpdated": "2026-02-09T17:01:03.234000",
      "token0TvlUsd": 30.644661714246105,
      "token1TvlUsd": 349.17303304778943,
      "totalSupply": "4432154182743125711323",
      "rewardsDetails": []
    },
    {
      "chainId": 42161,
      "protocol": "uniswapv3",
      "address": "0xfa392dbefd2d5ec891ef5aeb87397a89843a8260",
      "tvlUSD": "21678.005805623696",
      "feeApr": 0.5158048621383499,
      "rewardApr": 0,
      "lastUpdated": "2026-02-09T17:01:03.653000",
      "token0TvlUsd": 10509.213242056494,
      "token1TvlUsd": 11168.792563567204,
      "totalSupply": "2704192453330892671227",
      "rewardsDetails": []
    },
    {
      "chainId": 42161,
      "protocol": "uniswapv3",
      "address": "0xf08bdbc590c59cb7b27a8d224e419ef058952b5f",
      "tvlUSD": "4906.44964567729",
      "feeApr": 0.6966439682101331,
      "rewardApr": 0,
      "lastUpdated": "2026-02-09T17:01:03.633000",
      "token0TvlUsd": 2547.10053218584,
      "token1TvlUsd": 2359.3491134914498,
      "totalSupply": "149031727236076975641",
      "rewardsDetails": []
    },
    {
      "chainId": 42161,
      "protocol": "uniswapv3",
      "address": "0x2bcbdd577616357464cfe307bc67f9e820a66e80",
      "tvlUSD": "519.878011485617",
      "feeApr": 0,
      "rewardApr": 0,
      "lastUpdated": "2026-02-09T17:01:03.218000",
      "token0TvlUsd": 519.8686909419405,
      "token1TvlUsd": 0.00932054367649137,
      "totalSupply": "5605346197713434383",
      "rewardsDetails": []
    }
  ]
}