{
  "timestamp": "2026-01-04T08:05:10.776Z",
  "data": [
    {
      "chainId": 42161,
      "protocol": "uniswapv3",
      "address": "0x547a116a2622876ce1c8d19d41c683c8f7bec5c0",
      "tvlUSD": "2288.8837960649716",
      "feeApr": 0,
      "rewardApr": 0,
      "lastUpdated": "2026-01-04T08:00:41.779000",
      "token0TvlUsd": 2239.6820890649715,
      "token1TvlUsd": 49.201707,
      "totalSupply": "2199263355",
      "rewardsDetails": []
    },
    {
      "chainId": 42161,
      "protocol": "uniswapv3",
      "address": "0x52ee1ffba696c5e9b0bc177a9f8a3098420ea691",
      "tvlUSD": "10800.08081488858",
      "feeApr": 0.017517552549075156,
      "rewardApr": 0,
      "lastUpdated": "2026-01-04T08:00:41.774000",
      "token0TvlUsd": 1252.5256630936303,
      "token1TvlUsd": 9547.55515179495,
      "totalSupply": "1951497639819855809",
      "rewardsDetails": []
    },
    {
      "chainId": 42161,
      "protocol": "uniswapv3",
      "address": "0x330dfc5bc1a63a1dcf1cd5bc9ad3d5e5e61bcb6c",
      "tvlUSD": "624.5460371840667",
      "feeApr": 0.6806278787390432,
      "rewardApr": 0,
      "lastUpdated": "2026-01-04T08:00:41.694000",
      "token0TvlUsd": 578.6069460059404,
      "token1TvlUsd": 45.93909117812632,
      "totalSupply": "4432154182743125711323",
      "rewardsDetails": []
    },
    {
      "chainId": 42161,
      "protocol": "uniswapv3",
      "address": "0xfa392dbefd2d5ec891ef5aeb87397a89843a8260",
      "tvlUSD": "32640.62816583924",
      "feeApr": 0.42077270272065675,
      "rewardApr": 0,
      "lastUpdated": "2026-01-04T08:00:42.148000",
      "token0TvlUsd": 17609.62092804879,
      "token1TvlUsd": 15031.00723779045,
      "totalSupply": "2716411797312088954114",
      "rewardsDetails": []
    },
    {
      "chainId": 42161,
      "protocol": "uniswapv3",
      "address": "0xf08bdbc590c59cb7b27a8d224e419ef058952b5f",
      "tvlUSD": "6160.548283654598",
      "feeApr": 2.5024145438145253,
      "rewardApr": 0,
      "lastUpdated": "2026-01-04T08:00:42.082000",
      "token0TvlUsd": 1061.5587541293608,
      "token1TvlUsd": 5098.989529525237,
      "totalSupply": "149031727236076975641",
      "rewardsDetails": []
    },
    {
      "chainId": 42161,
      "protocol": "uniswapv3",
      "address": "0x2bcbdd577616357464cfe307bc67f9e820a66e80",
      "tvlUSD": "829.7077456355585",
      "feeApr": 0.2355210894068678,
      "rewardApr": 0,
      "lastUpdated": "2026-01-04T08:00:41.681000",
      "token0TvlUsd": 828.3352999186033,
      "token1TvlUsd": 1.3724457169552549,
      "totalSupply": "5605346197713434383",
      "rewardsDetails": []
    }
  ]
}