{
  "timestamp": "2026-05-15T01:37:43.551Z",
  "data": [
    {
      "chainId": 42161,
      "protocol": "uniswapv3",
      "address": "0x547a116a2622876ce1c8d19d41c683c8f7bec5c0",
      "tvlUSD": "548.6266676425241",
      "feeApr": 0.00018084228010365266,
      "rewardApr": 0,
      "lastUpdated": "2026-05-15T01:30:57.394000+00:00",
      "token0TvlUsd": 546.8933896425241,
      "token1TvlUsd": 1.733278,
      "totalSupply": "2190596432",
      "rewardsDetails": []
    },
    {
      "chainId": 42161,
      "protocol": "uniswapv3",
      "address": "0x52ee1ffba696c5e9b0bc177a9f8a3098420ea691",
      "tvlUSD": "11615.720954567747",
      "feeApr": 0.0015426892155446792,
      "rewardApr": 0,
      "lastUpdated": "2026-05-15T01:30:57.375000+00:00",
      "token0TvlUsd": 84.02237389075347,
      "token1TvlUsd": 11531.698580676994,
      "totalSupply": "2688559050890396213",
      "rewardsDetails": []
    },
    {
      "chainId": 42161,
      "protocol": "uniswapv3",
      "address": "0x330dfc5bc1a63a1dcf1cd5bc9ad3d5e5e61bcb6c",
      "tvlUSD": "334.8499453700015",
      "feeApr": 1.6736051114294732,
      "rewardApr": 0,
      "lastUpdated": "2026-05-15T01:30:57.306000+00:00",
      "token0TvlUsd": 13.661725074041296,
      "token1TvlUsd": 321.1882202959602,
      "totalSupply": "4432154182743125711323",
      "rewardsDetails": []
    },
    {
      "chainId": 42161,
      "protocol": "uniswapv3",
      "address": "0xfa392dbefd2d5ec891ef5aeb87397a89843a8260",
      "tvlUSD": "23845.4106680604",
      "feeApr": 0.005260618999694468,
      "rewardApr": 0,
      "lastUpdated": "2026-05-15T01:30:57.794000+00:00",
      "token0TvlUsd": 12039.448093928346,
      "token1TvlUsd": 11805.962574132058,
      "totalSupply": "2704192453330892671227",
      "rewardsDetails": []
    },
    {
      "chainId": 42161,
      "protocol": "uniswapv3",
      "address": "0xf08bdbc590c59cb7b27a8d224e419ef058952b5f",
      "tvlUSD": "2347.0027348718327",
      "feeApr": 2.1780469737959645,
      "rewardApr": 0,
      "lastUpdated": "2026-05-15T01:30:57.778000+00:00",
      "token0TvlUsd": 1152.8066674507725,
      "token1TvlUsd": 1194.1960674210602,
      "totalSupply": "76562182502833292876",
      "rewardsDetails": []
    },
    {
      "chainId": 42161,
      "protocol": "uniswapv3",
      "address": "0x2bcbdd577616357464cfe307bc67f9e820a66e80",
      "tvlUSD": "168.94011436571046",
      "feeApr": 0.06767541159147936,
      "rewardApr": 0,
      "lastUpdated": "2026-05-15T01:30:57.280000+00:00",
      "token0TvlUsd": 167.1153959281592,
      "token1TvlUsd": 1.8247184375512575,
      "totalSupply": "5231652462984837366",
      "rewardsDetails": []
    }
  ]
}