{
  "timestamp": "2025-12-13T06:05:11.693Z",
  "data": [
    {
      "chainId": 42161,
      "protocol": "uniswapv3",
      "address": "0x547a116a2622876ce1c8d19d41c683c8f7bec5c0",
      "tvlUSD": "2288.2803381257686",
      "feeApr": 0,
      "rewardApr": 0,
      "lastUpdated": "2025-12-13T06:01:24.981000",
      "token0TvlUsd": 2239.0971541363024,
      "token1TvlUsd": 49.18318398946615,
      "totalSupply": "2199263355",
      "rewardsDetails": []
    },
    {
      "chainId": 42161,
      "protocol": "uniswapv3",
      "address": "0x52ee1ffba696c5e9b0bc177a9f8a3098420ea691",
      "tvlUSD": "10461.264862354887",
      "feeApr": 0.2151485182705781,
      "rewardApr": 0,
      "lastUpdated": "2025-12-13T06:01:24.974000",
      "token0TvlUsd": 5448.785101772633,
      "token1TvlUsd": 5012.479760582253,
      "totalSupply": "1956716479867344104",
      "rewardsDetails": []
    },
    {
      "chainId": 42161,
      "protocol": "uniswapv3",
      "address": "0x330dfc5bc1a63a1dcf1cd5bc9ad3d5e5e61bcb6c",
      "tvlUSD": "620.2348356902952",
      "feeApr": 1.248716283413379,
      "rewardApr": 0,
      "lastUpdated": "2025-12-13T06:01:24.875000",
      "token0TvlUsd": 458.59087545096946,
      "token1TvlUsd": 161.64396023932576,
      "totalSupply": "4432154182743125711323",
      "rewardsDetails": []
    },
    {
      "chainId": 42161,
      "protocol": "uniswapv3",
      "address": "0xfa392dbefd2d5ec891ef5aeb87397a89843a8260",
      "tvlUSD": "32454.187952660122",
      "feeApr": 0.25618417435847635,
      "rewardApr": 0,
      "lastUpdated": "2025-12-13T06:01:25.450000",
      "token0TvlUsd": 20576.029733793395,
      "token1TvlUsd": 11878.158218866727,
      "totalSupply": "2716066989397453975949",
      "rewardsDetails": []
    },
    {
      "chainId": 42161,
      "protocol": "uniswapv3",
      "address": "0xf08bdbc590c59cb7b27a8d224e419ef058952b5f",
      "tvlUSD": "6852.83519408061",
      "feeApr": 0,
      "rewardApr": 0,
      "lastUpdated": "2025-12-13T06:01:25.394000",
      "token0TvlUsd": 6369.259393340494,
      "token1TvlUsd": 483.57580074011554,
      "totalSupply": "172098476826824777704",
      "rewardsDetails": []
    },
    {
      "chainId": 42161,
      "protocol": "uniswapv3",
      "address": "0x2bcbdd577616357464cfe307bc67f9e820a66e80",
      "tvlUSD": "803.0870897497566",
      "feeApr": 0.7398802916715278,
      "rewardApr": 0,
      "lastUpdated": "2025-12-13T06:01:24.860000",
      "token0TvlUsd": 757.8101563373094,
      "token1TvlUsd": 45.27693341244722,
      "totalSupply": "5605346197713434383",
      "rewardsDetails": []
    }
  ]
}