{
  "timestamp": "2025-12-02T14:17:44.197Z",
  "data": [
    {
      "chainId": 42161,
      "protocol": "uniswapv3",
      "address": "0x547a116a2622876ce1c8d19d41c683c8f7bec5c0",
      "tvlUSD": "2291.9866138290363",
      "feeApr": 0,
      "rewardApr": 0,
      "lastUpdated": "2025-12-02T14:01:21.851000",
      "token0TvlUsd": 2246.8488753560882,
      "token1TvlUsd": 45.13773847294795,
      "totalSupply": "2204730609",
      "rewardsDetails": []
    },
    {
      "chainId": 42161,
      "protocol": "uniswapv3",
      "address": "0x52ee1ffba696c5e9b0bc177a9f8a3098420ea691",
      "tvlUSD": "9722.35678135608",
      "feeApr": 0.008157993668032413,
      "rewardApr": 0,
      "lastUpdated": "2025-12-02T14:01:21.841000",
      "token0TvlUsd": 121.22710571435611,
      "token1TvlUsd": 9601.129675641725,
      "totalSupply": "1956716479867344104",
      "rewardsDetails": []
    },
    {
      "chainId": 42161,
      "protocol": "uniswapv3",
      "address": "0x330dfc5bc1a63a1dcf1cd5bc9ad3d5e5e61bcb6c",
      "tvlUSD": "572.9371312101432",
      "feeApr": 1.2347422277162456,
      "rewardApr": 0,
      "lastUpdated": "2025-12-02T14:01:21.723000",
      "token0TvlUsd": 70.53036095610777,
      "token1TvlUsd": 502.40677025403545,
      "totalSupply": "4432154182743125711323",
      "rewardsDetails": []
    },
    {
      "chainId": 42161,
      "protocol": "uniswapv3",
      "address": "0xfa392dbefd2d5ec891ef5aeb87397a89843a8260",
      "tvlUSD": "30152.586440223502",
      "feeApr": 0.5216296135892119,
      "rewardApr": 0,
      "lastUpdated": "2025-12-02T14:01:22.282000",
      "token0TvlUsd": 12493.735769135617,
      "token1TvlUsd": 17658.850671087883,
      "totalSupply": "2715261950902246862637",
      "rewardsDetails": []
    },
    {
      "chainId": 42161,
      "protocol": "uniswapv3",
      "address": "0xf08bdbc590c59cb7b27a8d224e419ef058952b5f",
      "tvlUSD": "6282.782373397383",
      "feeApr": 1.3223911331838447,
      "rewardApr": 0,
      "lastUpdated": "2025-12-02T14:01:22.229000",
      "token0TvlUsd": 1577.8555996360426,
      "token1TvlUsd": 4704.92677376134,
      "totalSupply": "171968852260107379114",
      "rewardsDetails": []
    },
    {
      "chainId": 42161,
      "protocol": "uniswapv3",
      "address": "0x2bcbdd577616357464cfe307bc67f9e820a66e80",
      "tvlUSD": "558.0484039866365",
      "feeApr": 0.07536437447215873,
      "rewardApr": 0,
      "lastUpdated": "2025-12-02T14:01:21.705000",
      "token0TvlUsd": 557.7717869421915,
      "token1TvlUsd": 0.2766170444449943,
      "totalSupply": "5605346197713434383",
      "rewardsDetails": []
    }
  ]
}