{
  "timestamp": "2025-11-10T00:17:06.925Z",
  "data": [
    {
      "chainId": 42161,
      "protocol": "uniswapv3",
      "address": "0x547a116a2622876ce1c8d19d41c683c8f7bec5c0",
      "tvlUSD": "7099.575664225178",
      "feeApr": 0.00012252465468945317,
      "rewardApr": 0.14852727635219173,
      "lastUpdated": "2025-11-10T00:01:18.797000",
      "token0TvlUsd": 3438.6554622251783,
      "token1TvlUsd": 3660.920202,
      "totalSupply": "6787321090",
      "rewardsDetails": []
    },
    {
      "chainId": 42161,
      "protocol": "uniswapv3",
      "address": "0x52ee1ffba696c5e9b0bc177a9f8a3098420ea691",
      "tvlUSD": "11982.95631525955",
      "feeApr": 0.7303335339936152,
      "rewardApr": 0,
      "lastUpdated": "2025-11-10T00:01:18.773000",
      "token0TvlUsd": 7503.745005375304,
      "token1TvlUsd": 4479.211309884246,
      "totalSupply": "1960952683462083396",
      "rewardsDetails": []
    },
    {
      "chainId": 42161,
      "protocol": "uniswapv3",
      "address": "0x330dfc5bc1a63a1dcf1cd5bc9ad3d5e5e61bcb6c",
      "tvlUSD": "804.4140957979171",
      "feeApr": 3.0083876412537465,
      "rewardApr": 0,
      "lastUpdated": "2025-11-10T00:01:18.688000",
      "token0TvlUsd": 26.587907876676844,
      "token1TvlUsd": 777.8261879212403,
      "totalSupply": "4432154182743125711323",
      "rewardsDetails": []
    },
    {
      "chainId": 42161,
      "protocol": "uniswapv3",
      "address": "0xfa392dbefd2d5ec891ef5aeb87397a89843a8260",
      "tvlUSD": "37900.77177630493",
      "feeApr": 1.596994049522635,
      "rewardApr": 0,
      "lastUpdated": "2025-11-10T00:01:19.206000",
      "token0TvlUsd": 7864.021506526683,
      "token1TvlUsd": 30036.750269778244,
      "totalSupply": "2717529942352646986140",
      "rewardsDetails": []
    },
    {
      "chainId": 42161,
      "protocol": "uniswapv3",
      "address": "0xf08bdbc590c59cb7b27a8d224e419ef058952b5f",
      "tvlUSD": "6786.448145160375",
      "feeApr": 5.590950814522428,
      "rewardApr": 0,
      "lastUpdated": "2025-11-10T00:01:19.164000",
      "token0TvlUsd": 6081.5922482956685,
      "token1TvlUsd": 704.8558968647068,
      "totalSupply": "178705735071537923405",
      "rewardsDetails": []
    },
    {
      "chainId": 42161,
      "protocol": "uniswapv3",
      "address": "0x2bcbdd577616357464cfe307bc67f9e820a66e80",
      "tvlUSD": "812.2737668612124",
      "feeApr": 0.6352543732608235,
      "rewardApr": 0,
      "lastUpdated": "2025-11-10T00:01:18.672000",
      "token0TvlUsd": 809.736314408707,
      "token1TvlUsd": 2.537452452505399,
      "totalSupply": "5605346197713434383",
      "rewardsDetails": []
    }
  ]
}